cool_math2
