Metadata-Version: 1.1
Name: cool-math2
Version: 1.6
Summary: Cool math
Home-page: https://github.com/missingdays/cool_math2
Author: missingdays
Author-email: rebovykin@gmail.com
License: UNKNOWN
Download-URL: https://github.com/missingdays/cool_math2/archive/1.6.tar.gz
Keywords: math
Platform: UNKNOWN
